pico2d/__init__.py
pico2d/pico2d.py
pico2d/pre_run.py
pico2d/data/ConsolaMalgun.ttf
pico2d-1.5.1.dist-info/licenses/LICENSE.txt
pico2d-1.5.1.dist-info/METADATA
pico2d-1.5.1.dist-info/WHEEL
pico2d-1.5.1.dist-info/entry_points.txt
pico2d-1.5.1.dist-info/top_level.txt
pico2d-1.5.1.dist-info/RECORD
